yt_experiments/__init__.py
yt_experiments/_version.py
yt_experiments/octree/converter.cp313-win_amd64.pyd
yt_experiments/octree/converter.pyx
yt_experiments/octree/tests/test_converter.py
yt_experiments/tests/test_yt_experiments.py
yt_experiments/tiled_grid/__init__.py
yt_experiments/tiled_grid/tiled_grids.py
yt_experiments/tiled_grid/tests/test_tiled_grid.py
yt_experiments-0.4.0.dist-info/licenses/LICENSE
yt_experiments-0.4.0.dist-info/METADATA
yt_experiments-0.4.0.dist-info/WHEEL
yt_experiments-0.4.0.dist-info/top_level.txt
yt_experiments-0.4.0.dist-info/RECORD
